{"content_hash":"edba5cf590f9cf57","findings":[{"rule_id":"PV-ENF-001","severity":"warning","message":"Equation `checkpoint_interval` has no preconditions","file":"contracts/checkpoint-v1.yaml","line":null,"contract_stem":"checkpoint-v1","suppressed":false},{"rule_id":"PV-ENF-002","severity":"error","message":"Equation `checkpoint_interval` has no lean_theorem — proof required","file":"contracts/checkpoint-v1.yaml","line":null,"contract_stem":"checkpoint-v1","suppressed":false},{"rule_id":"PV-ENF-002","severity":"error","message":"Equation `checkpoint_roundtrip` has no lean_theorem — proof required","file":"contracts/checkpoint-v1.yaml","line":null,"contract_stem":"checkpoint-v1","suppressed":false},{"rule_id":"PV-ENF-001","severity":"warning","message":"Equation `checkpoint_size` has no preconditions","file":"contracts/checkpoint-v1.yaml","line":null,"contract_stem":"checkpoint-v1","suppressed":false},{"rule_id":"PV-ENF-002","severity":"error","message":"Equation `checkpoint_size` has no lean_theorem — proof required","file":"contracts/checkpoint-v1.yaml","line":null,"contract_stem":"checkpoint-v1","suppressed":false}]}